<turret-class>
	<identifier>light_laser_turret</identifier>
	<name>Light Laser Turret</name>
	<visualization>
		<model-identifier>light_laser_turret</model-identifier>
		<visualization-parts>
			<visualization-part>
				<part-identifier>base</part-identifier>
				<style>
					<diffuse-color>
						<red>0.4</red>
						<green>0.4</green>
						<blue>0.5</blue>
						<opacity>1.0</opacity>
					</diffuse-color>
					<specular-color>
						<valid>false</valid>
						<red>1.0</red>
						<green>1.0</green>
						<blue>1.0</blue>
						<opacity>1.0</opacity>
					</specular-color>
					<shininess>
						<valid>false</valid>
						<value>40.0</value>
					</shininess>
					<program-identifier>default</program-identifier>
				</style>
			</visualization-part>
			<visualization-part>
				<part-identifier>gun</part-identifier>
				<style>
					<diffuse-color>
						<red>0.66</red>
						<green>0.66</green>
						<blue>0.75</blue>
						<opacity>1.0</opacity>
					</diffuse-color>
					<specular-color>
						<valid>false</valid>
						<red>1.0</red>
						<green>1.0</green>
						<blue>1.0</blue>
						<opacity>1.0</opacity>
					</specular-color>
					<shininess>
						<valid>false</valid>
						<value>40.0</value>
					</shininess>
					<program-identifier>default</program-identifier>
				</style>
			</visualization-part>
		</visualization-parts>
	</visualization>
	<slot-class-identifier>light_turret</slot-class-identifier>
	<orientation>
		<w>0.7071067812</w>
		<x>0</x>
		<y>0.7071067812</y>
		<z>0</z>
	</orientation>
	<reload-time>0.94</reload-time>
	<space-requirement>800</space-requirement>
	<energy-usage-per-shot>8</energy-usage-per-shot>
	<shot>
		<exit-position>
			<x>0.8</x>
			<y>0</y>
			<z>0.08</z>
		</exit-position>
		<exit-speed>40</exit-speed>
		<damage>10</damage>
		<life-time>3.0</life-time>
		<visualization>
			<model-identifier>laser_shot</model-identifier>
			<visualization-parts>
				<visualization-part>
					<part-identifier>laser_shot</part-identifier>
					<style>
						<diffuse-color>
							<red>0.7</red>
							<green>0.4</green>
							<blue>0.2</blue>
							<opacity>0.8</opacity>
						</diffuse-color>
						<specular-color>
							<valid>false</valid>
							<red>0</red>
							<green>0</green>
							<blue>0</blue>
							<opacity>1</opacity>
						</specular-color>
						<shininess>
							<valid>false</valid>
							<value>0.0</value>
						</shininess>
						<program-identifier>no_lighting</program-identifier>
					</style>
				</visualization-part>
			</visualization-parts>
		</visualization>
	</shot>
</turret-class>
